[
    {
        "id": 1,
        "name": "Stashbusters",
        "image": "",
        "deployed": "https://nameless-mesa-29731.herokuapp.com/",
        "github": "https://github.com/calliebn/stashbusters"
    },

    {
        "id": 2,
        "name": "Tech Blog",
        "image": "",
        "deployed": "https://immense-citadel-93901.herokuapp.com/ https://github.com/calliebn/tech_blog",
        "github": "https://github.com/calliebn/tech_blog"
    },

    {
        "id": 3,
        "name": "Budget Tracker",
        "image": "",
        "deployed": "https://enigmatic-tor-49600.herokuapp.com/",
        "github": "https://github.com/calliebn/budget_tracker"
    },

    {
        "id": 4,
        "name": "Carpe Diem",
        "image": "",
        "deployed": "https://calliebn.github.io/carpe_diem/",
        "github": "https://github.com/calliebn/carpe_diem"
    },

    {
        "id": 5,
        "name": "JavaScript Quiz",
        "image": "",
        "deployed": "https://calliebn.github.io/javascript_quiz/",
        "github": "https://github.com/calliebn/javascript_quiz"
    },

    {
        "id": 6,
        "name": "Employee Directory",
        "image": "",
        "deployed": "https://github.com/calliebn/employee_directory",
        "github": "https://github.com/calliebn/employee_directory"
    }
]